Workbook

Sheet Inputs
A1: ADBE alt-data workbook - Inputs (blue = hardcoded sourced input; black = formula)
A2: Built 2026-10-02. All inputs trace to Sources tab. Numbers retrieved via web-search snippets where the primary page was not fetchable; see notes.
A4: Input | B4: Value | C4: Unit | D4: Source | E4: URL
A5: Share price (close 2026-10-01) | B5: 241.28 | C5: USD | D5: Market data via web search (confirmed 2026-10-02) | E5: https://www.google.com/finance/quote/ADBE:NASDAQ
A6: Shares outstanding (10-Q cover, 2026-09-18) | B6: 389.2 | C6: M | D6: Adobe 10-Q Q3 FY26 cover page | E6: https://www.sec.gov/Archives/edgar/data/0000796343/000079634326000156/adbe-20260828.htm
A7: Q3 FY26 total revenue | B7: 6760 | C7: USD M | D7: Adobe Q3 FY26 press release (8-K Ex.99.1), 2026-09-10 | E7: https://www.sec.gov/Archives/edgar/data/0000796343/000079634326000147/adbeex991q326.htm
A8: Q3 FY26 C&MP subscription revenue | B8: 4651 | C8: USD M | D8: Adobe Q3 FY26 press release / 10-Q | E8: https://www.sec.gov/Archives/edgar/data/0000796343/000079634326000147/adbeex991q326.htm
A9: Q3 FY25 C&MP subscription revenue (recast) | B9: 4117 | C9: USD M | D9: Adobe Q3 FY26 10-Q | E9: https://www.sec.gov/Archives/edgar/data/0000796343/000079634326000156/adbe-20260828.htm
A10: Q3 FY26 BP&C subscription revenue | B10: 1905 | C10: USD M | D10: Adobe Q3 FY26 press release / 10-Q | E10: https://www.sec.gov/Archives/edgar/data/0000796343/000079634326000147/adbeex991q326.htm
A11: Q3 FY25 BP&C subscription revenue (recast) | B11: 1648 | C11: USD M | D11: Adobe Q3 FY26 10-Q | E11: https://www.sec.gov/Archives/edgar/data/0000796343/000079634326000156/adbe-20260828.htm
A12: 9M FY26 C&MP subscription revenue | B12: 13577 | C12: USD M | D12: Adobe Q3 FY26 10-Q | E12: https://www.sec.gov/Archives/edgar/data/0000796343/000079634326000156/adbe-20260828.htm
A13: 9M FY25 C&MP subscription revenue (recast) | B13: 12058 | C13: USD M | D13: Adobe Q3 FY26 10-Q | E13: https://www.sec.gov/Archives/edgar/data/0000796343/000079634326000156/adbe-20260828.htm
A14: 9M FY26 BP&C subscription revenue | B14: 5540 | C14: USD M | D14: Adobe Q3 FY26 10-Q | E14: https://www.sec.gov/Archives/edgar/data/0000796343/000079634326000156/adbe-20260828.htm
A15: 9M FY25 BP&C subscription revenue (recast) | B15: 4777 | C15: USD M | D15: Adobe Q3 FY26 10-Q | E15: https://www.sec.gov/Archives/edgar/data/0000796343/000079634326000156/adbe-20260828.htm
A16: FY26 revenue guidance low | B16: 26576 | C16: USD M | D16: Adobe Q3 FY26 press release targets | E16: https://www.sec.gov/Archives/edgar/data/0000796343/000079634326000147/adbeex991q326.htm
... A47: Q3 FY26 shares repurchased | B47: 9.5 | C47: M | D47: Adobe Q3 FY26 press release, verified 2026-10-02 | E47: https://www.sec.gov/Archives/edgar/data/796343/000079634326000147/adbeex991q326.htm
A49: Derived (formulas)
A50: Market cap (USD M) | B50: =Inputs!$B$5*Inputs!$B$6
A51: Net debt (USD M) | B51: =Inputs!$B$35-Inputs!$B$36
A52: Enterprise value (USD M) | B52: =B50+B51
A53: FY26 non-GAAP EPS midpoint | B53: =AVERAGE(Inputs!$B$22,Inputs!$B$23)
A54: P/E on FY26 non-GAAP EPS guide | B54: =B5/B53
A55: 9M FY26 FCF (OCF - capex, USD M) | B55: =Inputs!$B$31-Inputs!$B$32
A56: 9M FY26 FCF after SBC (USD M) | B56: =B55-Inputs!$B$33
A57: Annualized FCF (9M x 4/3, USD M) | B57: =B55*4/3
A58: EV / annualized FCF | B58: =B52/B57
A59: FCF yield on market cap (annualized) | B59: =B57/B50
A60: Q3 FY26 C&MP YoY growth | B60: =Inputs!$B$8/Inputs!$B$9-1
A61: Q3 FY26 BP&C YoY growth | B61: =Inputs!$B$10/Inputs!$B$11-1
A62: 9M FY26 C&MP YoY growth | B62: =Inputs!$B$12/Inputs!$B$13-1
A63: 9M FY26 BP&C YoY growth | B63: =Inputs!$B$14/Inputs!$B$15-1
A64: Implied Q4 FY26 C&MP revenue (guide mid - 9M) | B64: =AVERAGE(Inputs!$B$18,Inputs!$B$19)-Inputs!$B$12
A65: Implied FY26 ending ARR (USD M) | B65: =Inputs!$B$25*(1+Inputs!$B$24)
A66: AI-first ARR as % of Q3 ending ARR | B66: =Inputs!$B$28/Inputs!$B$26
A67: Q3 FY26 non-GAAP operating margin | B67: =Inputs!$B$42/Inputs!$B$7
A68: Q3 FY26 cRPO (USD M) | B68: =Inputs!$B$40*Inputs!$B$41

Sheet PriceVolume
A1: WS1: price vs volume decomposition (blue = sourced/modelled input; black = formula)
A3: Method (ws1 methods.md): cc growth = reported - FX gap; organic = cc - Semrush pts; implied volume/mix = (1+organic)/(1+price) - 1. Price contribution pts come from ws1 data/price_model.csv (list uplift x share repriced x renewal phase-in). Semrush Q3 FY26 revenue is an ESTIMATE.
A4: fiscal_quarter | B4: group | C4: scenario | D4: share_repriced | E4: sub_rev_m | F4: prior_year_sub_rev_m | G4: reported_growth_pct | H4: fx_adj_pts | I4: cc_growth_pct | J4: semrush_rev_m | K4: semrush_pts | L4: organic_cc_growth_pct | M4: price_contrib_pts | N4: implied_volume_mix_pct | O4: price_contrib_m2m_pts | P4: implied_volume_m2m_pct | Q4: fx_note
A5: FY25Q1 | B5: Creative & Marketing Professionals | C5: low_10pct | D5: 0.1 | E5: 3920 | F5: 3560 | G5: =(E5/F5-1)*100 | H5: -1 | I5: =G5-H5 | J5: 0 | K5: =J5/F5*100 | L5: =I5-K5 | M5: 0.83 | N5: =((1+L5/100)/(1+M5/100)-1)*100 | O5: 0.5 | P5: =((1+L5/100)/(1+O5/100)-1)*100 | Q5: total co. 10% rep / 11% cc; segment cc not disclosed -> company gap applied
A6: FY25Q1 | B6: Creative & Marketing Professionals | C6: base_20pct | D6: 0.2 | E6: 3920 | F6: 3560 | G6: =(E6/F6-1)*100 | H6: -1 | I6: =G6-H6 | J6: 0 | K6: =J6/F6*100 | L6: =I6-K6 | M6: 1.67 | N6: =((1+L6/100)/(1+M6/100)-1)*100 | O6: 1 | P6: =((1+L6/100)/(1+O6/100)-1)*100 | Q6: total co. 10% rep / 11% cc; segment cc not disclosed -> company gap applied
A7: FY25Q1 | B7: Creative & Marketing Professionals | C7: high_30pct | D7: 0.3 | E7: 3920 | F7: 3560 | G7: =(E7/F7-1)*100 | H7: -1 | I7: =G7-H7 | J7: 0 | K7: =J7/F7*100 | L7: =I7-K7 | M7: 2.5 | N7: =((1+L7/100)/(1+M7/100)-1)*100 | O7: 1.51 | P7: =((1+L7/100)/(1+O7/100)-1)*100 | Q7: total co. 10% rep / 11% cc; segment cc not disclosed -> company gap applied
A8: FY25Q1 | B8: Business Professionals & Consumers | C8: low_10pct | D8: 0.1 | E8: 1530 | F8: 1330 | G8: =(E8/F8-1)*100 | H8: -1 | I8: =G8-H8 | J8: 0 | K8: =J8/F8*100 | L8: =I8-K8 | M8: 1.78 | N8: =((1+L8/100)/(1+M8/100)-1)*100 | O8: 0 | P8: =((1+L8/100)/(1+O8/100)-1)*100 | Q8: total co. 10% rep / 11% cc; segment cc not disclosed -> company gap applied
A9: FY25Q1 | B9: Business Professionals & Consumers | C9: base_20pct | D9: 0.2 | E9: 1530 | F9: 1330 | G9: =(E9/F9-1)*100 | H9: -1 | I9: =G9-H9 | J9: 0 | K9: =J9/F9*100 | L9: =I9-K9 | M9: 3.51 | N9: =((1+L9/100)/(1+M9/100)-1)*100 | O9: 0 | P9: =((1+L9/100)/(1+O9/100)-1)*100 | Q9: total co. 10% rep / 11% cc; segment cc not disclosed -> company gap applied
A10: FY25Q1 | B10: Business Professionals & Consumers | C10: high_30pct | D10: 0.3 | E10: 1530 | F10: 1330 | G10: =(E10/F10-1)*100 | H10: -1 | I10: =G10-H10 | J10: 0 | K10: =J10/F10*100 | L10: =I10-K10 | M10: 5.2 | N10: =((1+L10/100)/(1+M10/100)-1)*100 | O10: 0 | P10: =((1+L10/100)/(1+O10/100)-1)*100 | Q10: total co. 10% rep / 11% cc; segment cc not disclosed -> company gap applied
A11: FY25Q2 | B11: Creative & Marketing Professionals | C11: low_10pct | D11: 0.1 | E11: 4020 | F11: 3655 | G11: =(E11/F11-1)*100 | H11: 0 | I11: =G11-H11 | J11: 0 | K11: =J11/F11*100 | L11: =I11-K11 | M11: 0.72 | N11: =((1+L11/100)/(1+M11/100)-1)*100 | O11: 0.4 | P11: =((1+L11/100)/(1+O11/100)-1)*100 | Q11: segment cc not found; DX sub 11% rep = cc -> 0 assumed
A12: FY25Q2 | B12: Creative & Marketing Professionals | C12: base_20pct | D12: 0.2 | E12: 4020 | F12: 3655 | G12: =(E12/F12-1)*100 | H12: 0 | I12: =G12-H12 | J12: 0 | K12: =J12/F12*100 | L12: =I12-K12 | M12: 1.44 | N12: =((1+L12/100)/(1+M12/100)-1)*100 | O12: 0.8 | P12: =((1+L12/100)/(1+O12/100)-1)*100 | Q12: segment cc not found; DX sub 11% rep = cc -> 0 assumed
A13: FY25Q2 | B13: Creative & Marketing Professionals | C13: high_30pct | D13: 0.3 | E13: 4020 | F13: 3655 | G13: =(E13/F13-1)*100 | H13: 0 | I13: =G13-H13 | J13: 0 | K13: =J13/F13*100 | L13: =I13-K13 | M13: 2.15 | N13: =((1+L13/100)/(1+M13/100)-1)*100 | O13: 1.2 | P13: =((1+L13/100)/(1+O13/100)-1)*100 | Q13: segment cc not found; DX sub 11% rep = cc -> 0 assumed
A14: FY25Q2 | B14: Business Professionals & Consumers | C14: low_10pct | D14: 0.1 | E14: 1600 | F14: 1391 | G14: =(E14/F14-1)*100 | H14: 0 | I14: =G14-H14 | J14: 0 | K14: =J14/F14*100 | L14: =I14-K14 | M14: 0.75 | N14: =((1+L14/100)/(1+M14/100)-1)*100 | O14: 0 | P14: =((1+L14/100)/(1+O14/100)-1)*100 | Q14: segment cc not found; DX sub 11% rep = cc -> 0 assumed
A15: FY25Q2 | B15: Business Professionals & Consumers | C15: base_20pct | D15: 0.2 | E15: 1600 | F15: 1391 | G15: =(E15/F15-1)*100 | H15: 0 | I15: =G15-H15 | J15: 0 | K15: =J15/F15*100 | L15: =I15-K15 | M15: 1.46 | N15: =((1+L15/100)/(1+M15/100)-1)*100 | O15: 0 | P15: =((1+L15/100)/(1+O15/100)-1)*100 | Q15: segment cc not found; DX sub 11% rep = cc -> 0 assumed
A16: FY25Q2 | B16: Business Professionals & Consumers | C16: high_30pct | D16: 0.3 | E16: 1600 | F16: 1391 | G16: =(E16/F16-1)*100 | H16: 0 | I16: =G16-H16 | J16: 0 | K16: =J16/F16*100 | L16: =I16-K16 | M16: 2.15 | N16: =((1+L16/100)/(1+M16/100)-1)*100 | O16: 0 | P16: =((1+L16/100)/(1+O16/100)-1)*100 | Q16: segment cc not found; DX sub 11% rep = cc -> 0 assumed
... A46: FY26Q3 | B46: Business Professionals & Consumers | C46: high_30pct | D46: 0.3 | E46: 1905 | F46: 1648 | G46: =(E46/F46-1)*100 | H46: 1 | I46: =G46-H46 | J46: 0 | K46: =J46/F46*100 | L46: =I46-K46 | M46: 0.06 | N46: =((1+L46/100)/(1+M46/100)-1)*100 | O46: 0.39 | P46: =((1+L46/100)/(1+O46/100)-1)*100 | Q46: C&MP 13% rep / 12% cc; BP&C 16% / 15%
A48: Price-change log (ws1 data/price_log.csv; list prices, US unless noted)
A49: effective_date | B49: announce_date | C49: product | D49: plan_type | E49: region | F49: old_price | G49: new_price | H49: pct_change | I49: applies_to | J49: source_url | K49: notes
A50: 2022-04-27 | B50: 2022-03-22 | C50: Creative Cloud for teams All Apps | D50: teams, annual (per license/mo) | E50: North America | F50: 79.99 | G50: 84.99 | H50: =(G50/F50-1)*100 | I50: renewal | J50: https://blog.adobe.com/en/publish/2022/03/22/creative-cloud-offering-price-update | K50: Applied at next renewal on/after 2022-04-27; enterprise (ETLA) also raised, amounts not public. Adobe blog.
A51: 2022-04-27 | B51: 2022-03-22 | C51: Creative Cloud for teams Single App | D51: teams, annual (per license/mo) | E51: North America | F51: 33.99 | G51: 35.99 | H51: =(G51/F51-1)*100 | I51: renewal | J51: https://www.cgchannel.com/2022/03/adobe-to-raise-price-of-creative-cloud-subscriptions/ | K51: Teams single-app +$2; individual single-app plans explicitly unchanged in 2022.
A52: 2022-04-27 | B52: 2022-03-22 | C52: Creative Cloud All Apps (individual) | D52: individual, month-to-month | E52: North America | F52: 79.49 | G52: 82.49 | H52: =(G52/F52-1)*100 | I52: renewal | J52: https://blog.adobe.com/en/publish/2022/03/22/creative-cloud-offering-price-update | K52: Only the month-to-month individual All Apps plan changed in 2022; annual plans unchanged.
A53: 2022-08-08 | B53: 2022-08-08 | C53: Acrobat Pro (individual) | D53: individual, annual billed monthly | E53: US | F53: 14.99 | G53: 19.99 | H53: =(G53/F53-1)*100 | I53: new | J53: https://www.schneider.im/adobe-acrobat-pro-price-increase-reminder/ | K53: Adobe described the Acrobat Pro increase as ~40% (some SKUs); community reports $15->$20/mo. New customers from 2022-08-08.
A54: 2023-07-01 | B54: 2022-08-08 | C54: Acrobat Pro (individual) - existing subscribers | D54: individual, annual billed monthly | E54: US | F54: 14.99 | G54: 19.99 | H54: =(G54/F54-1)*100 | I54: renewal | J54: https://community.adobe.com/t5/acrobat-discussions/2023-price-increase-for-adobe-pro/m-p/13536125 | K54: Existing subscribers with an active licence at 2022-08-08 repriced from 2023-07-01 at renewal.
A55: 2023-11-01 | B55: 2023-09-13 | C55: Creative Cloud All Apps (individual) | D55: individual, annual billed monthly | E55: NA, Central/South America, Europe | F55: 54.99 | G55: 59.99 | H55: =(G55/F55-1)*100 | I55: all | J55: https://blog.adobe.com/en/publish/2023/09/13/ai-creative-cloud-release-pricing-update | K55: New subscribers immediately; existing at next renewal. Firefly generative credits bundled. Adobe blog + helpx.
A56: 2023-11-01 | B56: 2023-09-13 | C56: Creative Cloud All Apps (individual) | D56: individual, month-to-month | E56: NA, Central/South America, Europe | F56: 82.49 | G56: 89.99 | H56: =(G56/F56-1)*100 | I56: all | J56: https://www.dpreview.com/news/1676880155/adobe-increases-creative-cloud-pricing-takes-firefly-out-of-beta/ | K56: dpreview quotes $82.50->$90.
A57: 2023-11-01 | B57: 2023-09-13 | C57: Creative Cloud Single App (Photoshop, Illustrator, Premiere Pro etc.) | D57: individual, annual billed monthly | E57: NA, Central/South America, Europe | F57: 20.99 | G57: 22.99 | H57: =(G57/F57-1)*100 | I57: all | J57: https://helpx.adobe.com/sg/x-productkb/policy-pricing/subscription-price-increase-2023-individual-plans.html | K57: PetaPixel: $21->$23/mo annual-billed-monthly.
A58: 2023-11-01 | B58: 2023-09-13 | C58: Creative Cloud Single App | D58: individual, month-to-month | E58: NA, Central/South America, Europe | F58: 31.49 | G58: 34.49 | H58: =(G58/F58-1)*100 | I58: all | J58: https://petapixel.com/2023/09/15/adobe-hikes-creative-cloud-prices-as-it-reports-record-revenue/ | K58: PetaPixel/dpreview: $31.50->$34.50.
A59: 2023-11-01 | B59: 2023-09-13 | C59: Creative Cloud for teams All Apps | D59: teams, annual (per license/mo) | E59: NA, Central/South America, Europe | F59: 84.99 | G59: 89.99 | H59: =(G59/F59-1)*100 | I59: renewal | J59: https://helpx.adobe.com/x-productkb/policy-pricing/subscription-price-increase-2023-enterprise-teams.html | K59: helpx 'Creative Cloud for teams and enterprise 2023 pricing changes'.
A60: 2023-11-01 | B60: 2023-09-13 | C60: Creative Cloud for teams Single App | D60: teams, annual (per license/mo) | E60: NA, Central/South America, Europe | F60: 35.99 | G60: 37.99 | H60: =(G60/F60-1)*100 | I60: renewal | J60: https://helpx.adobe.com/x-productkb/policy-pricing/subscription-price-increase-2023-enterprise-teams.html
A61: 2023-11-01 | B61: 2023-09-13 | C61: Firefly Premium (100 credits/mo) - NEW SKU | D61: individual, monthly | E61: Global | G61: 4.99 | I61: new | J61: https://www.dpreview.com/news/1676880155/adobe-increases-creative-cloud-pricing-takes-firefly-out-of-beta/ | K61: New add-on SKU, not a price change (excluded from price model).
A62: 2024-03-05 | B62: 2023-09-13 | C62: Nov-2023 wave extended to Africa, Asia, Australia | D62: individual + teams | E62: Africa, Asia, Australia | I62: all | J62: https://helpx.adobe.com/sg/x-productkb/policy-pricing/subscription-price-increase-2023-individual-plans.html | K62: Same ~10% structure as Nov-2023; local-currency amounts not captured.
A63: 2025-01-15 | B63: 2024-12-15 | C63: Photography plan 20GB (Photoshop+Lightroom) | D63: individual, annual billed monthly | E63: Worldwide | F63: 9.99 | G63: 14.99 | H63: =(G63/F63-1)*100 | I63: renewal | J63: https://blog.adobe.com/en/publish/2024/12/15/all-new-photography-innovations-pricing-updates | K63: Existing monthly-billed subscribers +50% at renewal; could keep $9.99 equivalent by switching to prepaid annual ($119.88). Retired for NEW subscribers.
A64: 2025-01-15 | B64: 2024-12-15 | C64: Photography plan - new-subscriber entry point (20GB retired, 1TB only) | D64: individual, annual billed monthly | E64: Worldwide | F64: 9.99 | G64: 19.99 | H64: =(G64/F64-1)*100 | I64: new | J64: https://petapixel.com/2024/12/18/adobe-is-ditching-their-cheapest-photography-plan-for-new-customers-now-what/ | K64: Mix effect for new subscribers only; 1TB plan price itself unchanged at $19.99.
A65: 2025-01-15 | B65: 2024-12-15 | C65: Lightroom (1TB) plan | D65: individual, annual billed monthly | E65: Worldwide | F65: 9.99 | G65: 11.99 | H65: =(G65/F65-1)*100 | I65: all | J65: https://blog.adobe.com/en/publish/2024/12/15/all-new-photography-innovations-pricing-updates | K65: Prepaid annual unchanged at $119.88; Lightroom Classic added to plan.
A66: 2025-02-12 | B66: 2025-02-12 | C66: Firefly Standard - NEW SKU | D66: individual, monthly | E66: Global | G66: 9.99 | I66: new | J66: https://techcrunch.com/2025/02/12/adobe-launches-firefly-ai-subscriptions/ | K66: Launch (promotional) price; Adobe said subject to change 2025-03-15. New SKU, excluded from price model (mix).
A67: 2025-02-12 | B67: 2025-02-12 | C67: Firefly Pro - NEW SKU | D67: individual, monthly | E67: Global | G67: 29.99 | I67: new | J67: https://petapixel.com/2025/02/18/adobe-now-sells-firefly-plans-but-photographers-dont-need-them-yet/ | K67: Launch price $29.99. By 2026 the lineup is Standard $9.99 / Pro $19.99 / Pro Plus $49.99 / Premium $199.99 (re-tier date UNAVAILABLE).
A68: 2026-09-01 | C68: Firefly lineup as of Sep-2026: Standard/Pro/Pro Plus/Premium | D68: individual, monthly | E68: US | I68: new | J68: https://aiproductivity.ai/pricing/adobe-firefly/ | K68: Third-party price tracker; Pro Plus & Premium 30% off first year through 2026-08-26. Date of re-tier from $29.99 Pro UNAVAILABLE.
A69: 2025-06-17 | B69: 2025-05-20 | C69: Firefly generative credit add-on pack (100 credits) | D69: add-on | E69: Global | G69: 4.99 | I69: new | J69: https://helpx.adobe.com/creative-cloud/apps/generative-ai/generative-credits-faq.html | K69: helpx Generative credits FAQ; larger packs (2,000/4,000/7,000 credits) exist, prices not captured. Credit-tracking enforced from 2025-06-17 (PetaPixel 2025-06-24).
A70: 2025-06-17 | B70: 2025-05-20 | C70: Creative Cloud All Apps -> Creative Cloud Pro (individual) | D70: individual, annual billed monthly | E70: North America | F70: 59.99 | G70: 69.99 | H70: =(G70/F70-1)*100 | I70: all | J70: https://helpx.adobe.com/account/individual/subscriptions-and-plans/plan-types-and-eligibility/changes-to-individual-plan.html | K70: Existing All Apps members auto-renamed to Pro; new price at first renewal on/after 2025-06-17. New subscribers immediately.
A71: 2025-06-17 | B71: 2025-05-20 | C71: Creative Cloud Standard (individual) - NEW lower tier | D71: individual, annual billed monthly | E71: North America | F71: 59.99 | G71: 54.99 | H71: =(G71/F71-1)*100 | I71: new | J71: https://www.fastcompany.com/91337900/adobe-creative-cloud-pro | K71: Downgrade option for existing All Apps members (-8.3% vs old All Apps price); fewer generative credits. Realised uplift on base therefore < list +16.7%.
A72: 2025-06-17 | B72: 2025-05-20 | C72: Creative Cloud for teams All Apps -> Creative Cloud Pro for teams | D72: teams, annual (per license/mo) | E72: North America | F72: 89.99 | G72: 99.99 | H72: =(G72/F72-1)*100 | I72: renewal | J72: https://helpx.adobe.com/account/individual/subscriptions-and-plans/plan-types-and-eligibility/changes-to-teams-plan.html | K72: Teams All Apps renamed Pro for teams; old 'Pro Edition' renamed 'Pro Plus'.
A73: 2025-06-17 | B73: 2025-05-20 | C73: Creative Cloud Single App (individual) | D73: individual, annual billed monthly | E73: North America | F73: 22.99 | G73: 22.99 | H73: =(G73/F73-1)*100 | I73: all | J73: https://helpx.adobe.com/account/individual/subscriptions-and-plans/plan-types-and-eligibility/changes-to-individual-plan.html | K73: Explicitly NO price change for single-app subscribers in June 2025.
A74: 2025-06-17 | B74: 2025-05-20 | C74: Creative Cloud for teams Single App | D74: teams, annual (per license/mo) | E74: North America | F74: 37.99 | G74: 37.99 | H74: =(G74/F74-1)*100 | I74: all | J74: https://helpx.adobe.com/account/individual/subscriptions-and-plans/plan-types-and-eligibility/changes-to-teams-plan.html | K74: Unchanged at $37.99 (licenseware summary).
A75: 2025-08-19 | B75: 2025-08-19 | C75: Acrobat Studio - NEW SKU (individual $24.99 / teams $29.99) | D75: individual + teams, annual billed monthly | E75: US | G75: 24.99 | I75: new | J75: https://news.adobe.com/news/2025/08/acrobat-studio-delivers-new-ai-powered-home-for-productivity-creativity | K75: Upsell tier above Acrobat Pro ($19.99); existing Standard/Pro customers offered up to 15% off to upgrade through 2026-10-31. Mix, not price.
A76: 2026-01-15 | C76: Acrobat / Creative Cloud consumer 'broad increase' (claimed) | D76: individual | E76: US | I76: renewal | J76: https://ravody.com/adobe-creative-cloud-acrobat-pricing-2026/ | K76: LOW CONFIDENCE: only secondary blogs (ravody, redresscompliance) assert a 2026-01-15 consumer increase; no Adobe page or major outlet found. Acrobat Standard individual now lists $14.99 vs earlier $12.99 (+15.4%) per xodo/photutorial, date of that change UNAVAILABLE.
A77: 2026-04-01 | B77: 2026-02-05 | C77: Acrobat Standard for business (Teams/Enterprise, VIP) | D77: teams, annual (per license/mo) | E77: Global (VIP) | I77: renewal | J77: https://www.schneider.im/adobe-acrobat-standard-price-increase-announcement/ | K77: Adobe reseller notice; percentage NOT disclosed in sources. Current teams list $16.99/user/mo (xodo).
A78: 2026-06-01 | B78: 2026-02-01 | C78: VIP Marketplace list-price increase, most Creative Cloud & Acrobat SKUs (teams/enterprise) | D78: teams/enterprise, annual | E78: Global (VIP) | I78: renewal | J78: https://www.schneider.im/adobe-acrobat-creative-cloud-others-price-increases/ | K78: Schneider IT: broad increase esp. volume tiers (>=10 licences); Express, Stock, AI Assistant, Sign out of scope. Redress: Acrobat Pro teams $22.99->$23.99 (+4.3%); claims 5-22% by SKU. Enterprise ETLAs protected to term end.
A79: 2026-06-01 | B79: 2026-02-01 | C79: Acrobat Pro for teams | D79: teams, annual (per license/mo) | E79: Global (VIP) | F79: 22.99 | G79: 23.99 | H79: =(G79/F79-1)*100 | I79: renewal | J79: https://redresscompliance.com/adobe-price-increase-2026-impact | K79: Secondary source (licensing consultancy).
A80: 2023-01-01 | C80: Adobe Express Premium | D80: individual, monthly or annual | E80: US | F80: 9.99 | G80: 9.99 | H80: =(G80/F80-1)*100 | I80: all | J80: https://www.g2.com/products/adobe-express/pricing | K80: No price change found 2023-2026: $9.99/mo or $99.99/yr throughout (G2/Capterra listings). Date column = start of observation window.

Sheet SeatCompression
A1: WS2: revenue per creative worker / seat compression (blue = sourced input; black = formula)
A2: MISMATCH: Adobe revenue is GLOBAL (fiscal year ending Nov/Dec); employment is US-only BLS OEWS wage-and-salary (May reference). Indices only, not per-seat dollars.
A4: A. BLS OEWS national employment (May) and Adobe revenue (USD bn), 2019-2025
A5: year | B5: 27-1024 | C5: 27-1011 | D5: 27-1014 | E5: 27-4032 | F5: 27-4021 | G5: 11-2021 | H5: 13-1161 | I5: creative5_sum (f) | J5: marketing2_sum (f) | K5: DM_rev_bn | L5: creative_rev_bn | M5: total_rev_bn | N5: creative5_idx (f) | O5: DM_rev_idx (f) | P5: DM_rev_per_worker_idx (f) | Q5: creative_rev_per_worker_idx (f)
A6: 2019 | B6: 215930 | C6: 42890 | D6: 29340 | E6: 27570 | F6: 50620 | G6: 263680 | H6: 678500 | I6: =SUM(B6:F6) | J6: =G6+H6 | K6: 7.71 | L6: 6.48 | M6: 11.17 | N6: =I6/I$6*100 | O6: =K6/K$6*100 | P6: =(K6/I6)/(K$6/I$6)*100 | Q6: =IF(L6="","",(L6/I6)/(L$6/I$6)*100)
A7: 2020 | B7: 201440 | C7: 40950 | D7: 26460 | E7: 22410 | F7: 41600 | G7: 270200 | H7: 690160 | I7: =SUM(B7:F7) | J7: =G7+H7 | K7: 9.23 | L7: 7.74 | M7: 12.87 | N7: =I7/I$6*100 | O7: =K7/K$6*100 | P7: =(K7/I7)/(K$6/I$6)*100 | Q7: =IF(L7="","",(L7/I7)/(L$6/I$6)*100)
A8: 2021 | B8: 204040 | C8: 42080 | D8: 20430 | E8: 28030 | F8: 38420 | G8: 278690 | H8: 727540 | I8: =SUM(B8:F8) | J8: =G8+H8 | K8: 11.52 | L8: 9.55 | M8: 15.79 | N8: =I8/I$6*100 | O8: =K8/K$6*100 | P8: =(K8/I8)/(K$6/I$6)*100 | Q8: =IF(L8="","",(L8/I8)/(L$6/I$6)*100)
A9: 2022 | B9: 211890 | C9: 54470 | D9: 35990 | E9: 32080 | F9: 47380 | G9: 328570 | H9: 798620 | I9: =SUM(B9:F9) | J9: =G9+H9 | K9: 12.84 | L9: 10.46 | M9: 17.61 | N9: =I9/I$6*100 | O9: =K9/K$6*100 | P9: =(K9/I9)/(K$6/I$6)*100 | Q9: =IF(L9="","",(L9/I9)/(L$6/I$6)*100)
A10: 2023 | B10: 212720 | C10: 51200 | D10: 29940 | E10: 29240 | F10: 53630 | G10: 368940 | H10: 846370 | I10: =SUM(B10:F10) | J10: =G10+H10 | K10: 14.22 | L10: 11.52 | M10: 19.41 | N10: =I10/I$6*100 | O10: =K10/K$6*100 | P10: =(K10/I10)/(K$6/I$6)*100 | Q10: =IF(L10="","",(L10/I10)/(L$6/I$6)*100)
A11: 2024 | B11: 214260 | C11: 50370 | D11: 21280 | E11: 28860 | F11: 51230 | G11: 384980 | H11: 861140 | I11: =SUM(B11:F11) | J11: =G11+H11 | K11: 15.86 | L11: 12.68 | M11: 21.51 | N11: =I11/I$6*100 | O11: =K11/K$6*100 | P11: =(K11/I11)/(K$6/I$6)*100 | Q11: =IF(L11="","",(L11/I11)/(L$6/I$6)*100)
A12: 2025 | B12: 197830 | C12: 53070 | D12: 19970 | E12: 25610 | F12: 51760 | G12: 395240 | H12: 899580 | I12: =SUM(B12:F12) | J12: =G12+H12 | K12: 17.65 | M12: 23.77 | N12: =I12/I$6*100 | O12: =K12/K$6*100 | P12: =(K12/I12)/(K$6/I$6)*100 | Q12: =IF(L12="","",(L12/I12)/(L$6/I$6)*100)
A14: B. Achieved revenue-per-US-creative-worker growth (formulas)
A15: DM rev per creative worker CAGR FY19-FY25 | B15: =((K12/I12)/(K6/I6))^(1/(12-6))-1
A16: Creative rev per creative worker CAGR FY19-FY24 | B16: =((L11/I11)/(L6/I6))^(1/(11-6))-1
A17: DM rev per creative worker growth FY24->FY25 | B17: =(K12/I12)/(K11/I11)-1
A18: Creative5 employment change May-24 -> May-25 | B18: =I12/I11-1
A19: Graphic designers change May-24 -> May-25 | B19: =B12/B11-1
A21: C. Required per-worker growth to sustain target ARR growth under headcount scenarios (formulas)
A22: Target ARR growth | B22: 0.1
A23: Creative5 employment base (May 2025) | B23: =I12
A24: scenario | B24: annual headcount growth | C24: emp 2026 (f) | D24: emp 2027 (f) | E24: emp 2028 (f) | F24: required per-worker growth (f) | G24: achieved FY19-25 CAGR | H24: gap (achieved - required)
A25: Flat headcount | B25: 0 | C25: =$B$23*(1+B25)^1 | D25: =$B$23*(1+B25)^2 | E25: =$B$23*(1+B25)^3 | F25: =(1+$B$22)/(1+B25)-1 | G25: =$B$15 | H25: =G25-F25
A26: -3%/yr headcount | B26: -0.03 | C26: =$B$23*(1+B26)^1 | D26: =$B$23*(1+B26)^2 | E26: =$B$23*(1+B26)^3 | F26: =(1+$B$22)/(1+B26)-1 | G26: =$B$15 | H26: =G26-F26
A27: -7%/yr headcount | B27: -0.07 | C27: =$B$23*(1+B27)^1 | D27: =$B$23*(1+B27)^2 | E27: =$B$23*(1+B27)^3 | F27: =(1+$B$22)/(1+B27)-1 | G27: =$B$15 | H27: =G27-F27
A28: BLS 2024-34 projection CAGR | B28: 0.0025 | C28: =$B$23*(1+B28)^1 | D28: =$B$23*(1+B28)^2 | E28: =$B$23*(1+B28)^3 | F28: =(1+$B$22)/(1+B28)-1 | G28: =$B$15 | H28: =G28-F28
A29: BLS 2025-35 projection CAGR (Sep-2026 OOH update) | B29: -0.0005 | C29: =$B$23*(1+B29)^1 | D29: =$B$23*(1+B29)^2 | E29: =$B$23*(1+B29)^3 | F29: =(1+$B$22)/(1+B29)-1 | G29: =$B$15 | H29: =G29-F29
A30: Postings-based (Indeed creative YoY x beta) | B30: 0.0074 | C30: =$B$23*(1+B30)^1 | D30: =$B$23*(1+B30)^2 | E30: =$B$23*(1+B30)^3 | F30: =(1+$B$22)/(1+B30)-1 | G30: =$B$15 | H30: =G30-F30
A31: Trend: 2019-2025 OEWS CAGR | B31: -0.0084 | C31: =$B$23*(1+B31)^1 | D31: =$B$23*(1+B31)^2 | E31: =$B$23*(1+B31)^3 | F31: =(1+$B$22)/(1+B31)-1 | G31: =$B$15 | H31: =G31-F31
A32: Stress: repeat of 2024->2025 drop | B32: -0.0485 | C32: =$B$23*(1+B32)^1 | D32: =$B$23*(1+B32)^2 | E32: =$B$23*(1+B32)^3 | F32: =(1+$B$22)/(1+B32)-1 | G32: =$B$15 | H32: =G32-F32
A34: D. Advertising holding-company year-end headcount (blue) with 2019=100 index (formula)
A35: year | B35: Interpublic | C35: Omnicom | D35: Publicis | E35: WPP | F35: Interpublic idx (f) | G35: Omnicom idx (f) | H35: Publicis idx (f) | I35: WPP idx (f)
A36: 2019 | B36: 54300 | C36: 70000 | D36: 83235 | E36: 106478 | F36: =IF(B36="","",B36/B$36*100) | G36: =IF(C36="","",C36/C$36*100) | H36: =IF(D36="","",D36/D$36*100) | I36: =IF(E36="","",E36/E$36*100)
A37: 2020 | B37: 50200 | C37: 64100 | D37: 79051 | E37: 99830 | F37: =IF(B37="","",B37/B$36*100) | G37: =IF(C37="","",C37/C$36*100) | H37: =IF(D37="","",D37/D$36*100) | I37: =IF(E37="","",E37/E$36*100)
A38: 2021 | B38: 55600 | C38: 71700 | D38: 88531 | E38: 109382 | F38: =IF(B38="","",B38/B$36*100) | G38: =IF(C38="","",C38/C$36*100) | H38: =IF(D38="","",D38/D$36*100) | I38: =IF(E38="","",E38/E$36*100)
A39: 2022 | B39: 58400 | C39: 74200 | D39: 98022 | E39: 115473 | F39: =IF(B39="","",B39/B$36*100) | G39: =IF(C39="","",C39/C$36*100) | H39: =IF(D39="","",D39/D$36*100) | I39: =IF(E39="","",E39/E$36*100)
A40: 2023 | B40: 57400 | C40: 75900 | D40: 103295 | E40: 114173 | F40: =IF(B40="","",B40/B$36*100) | G40: =IF(C40="","",C40/C$36*100) | H40: =IF(D40="","",D40/D$36*100) | I40: =IF(E40="","",E40/E$36*100)
A41: 2024 | B41: 53300 | C41: 74900 | D41: 108179 | E41: 108044 | F41: =IF(B41="","",B41/B$36*100) | G41: =IF(C41="","",C41/C$36*100) | H41: =IF(D41="","",D41/D$36*100) | I41: =IF(E41="","",E41/E$36*100)
A42: 2025 | C42: 120000 | D42: 114000 | E42: 98655 | F42: =IF(B42="","",B42/B$36*100) | G42: =IF(C42="","",C42/C$36*100) | H42: =IF(D42="","",D42/D$36*100) | I42: =IF(E42="","",E42/E$36*100)
A44: E. Indeed Hiring Lab US job postings index (Feb-2020 = 100), monthly (blue); latest month and YoY (formula)
A45: month | B45: Arts & Entertainment | C45: Marketing | D45: Media & Communications | E45: Software Development | F45: Total (SA) | G45: Total (NSA)
A46: 2020-02 | B46: 99.18 | C46: 100.6 | D46: 101.1 | E46: 99.65 | F46: 100.05 | G46: 100.6
A47: 2020-03 | B47: 92.69 | C47: 93.69 | D47: 94.49 | E47: 98.22 | F47: 94.52 | G47: 97.26
A48: 2020-04 | B48: 58.36 | C48: 53.29 | D48: 58.99 | E48: 77.41 | F48: 68.2 | G48: 71.44
A49: 2020-05 | B49: 49.58 | C49: 44.71 | D49: 51.01 | E49: 66.54 | F49: 62.9 | G49: 66.78
A50: 2020-06 | B50: 51.94 | C50: 47.64 | D50: 54.75 | E50: 65.23 | F50: 70.05 | G50: 73.34
A51: 2020-07 | B51: 56.51 | C51: 53.13 | D51: 59.69 | E51: 67.32 | F51: 78.26 | G51: 80.73
A52: 2020-08 | B52: 59.86 | C52: 58.31 | D52: 60.2 | E52: 70.06 | F52: 82.96 | G52: 86.65
A53: 2020-09 | B53: 63.48 | C53: 65.6 | D53: 64.47 | E53: 72.94 | F53: 86.31 | G53: 90.47
A54: 2020-10 | B54: 67.48 | C54: 72.18 | D54: 73.23 | E54: 77.78 | F54: 90.46 | G54: 95.18
A55: 2020-11 | B55: 70.28 | C55: 79.14 | D55: 77.08 | E55: 83.61 | F55: 93.54 | G55: 97.13
A56: 2020-12 | B56: 73.62 | C56: 85.18 | D56: 80.3 | E56: 89.97 | F56: 94.84 | G56: 94.7
A57: 2021-01 | B57: 77 | C57: 89.52 | D57: 82.85 | E57: 93.41 | F57: 97.68 | G57: 95.65
... A125: 2026-09 | B125: 84.19 | C125: 76.32 | D125: 70.73 | E125: 76.91 | F125: 103.15 | G125: 107.48
A126: Latest YoY % (f) | B126: =B125/B113-1 | C126: =C125/C113-1 | D126: =D125/D113-1 | E126: =E125/E113-1 | F126: =F125/F113-1 | G126: =G125/G113-1

Sheet TaskExposure
A1: WS3: AI task exposure by creative-workflow stage (blue = computed from O*NET + Eloundou labels; black = formula)
A3: Highly exposed = Eloundou E1 or E2 (gamma). Weights: equal within occupation; occupations by BLS OEWS May 2021 employment. Monetization = analyst ESTIMATE (ws3 data/stage_monetization.csv).
A4: Scheme: 4 creative occupations (27-1024, 27-1011, 27-1014, 27-4032)
A5: stage | B5: monetization | C5: n_tasks | D5: stage_weight_share | E5: share_highly_exposed_human | F5: share_highly_exposed_gpt4 | G5: mean_beta_human | H5: exposed_weight_human (formula) | I5: exposed_weight_gpt4 (formula)
A6: ideation/concepting | B6: seat | C6: 10 | D6: 0.218 | E6: 1 | F6: 1 | G6: 0.5095 | H6: =D6*E6 | I6: =D6*F6
A7: asset generation | B7: seat | C7: 13 | D7: 0.2209 | E7: 0.9813 | F7: 1 | G7: 0.4906 | H7: =D7*E7 | I7: =D7*F7
A8: editing/retouching/compositing | B8: seat | C8: 16 | D8: 0.067 | E8: 0.8765 | F8: 1 | G8: 0.5309 | H8: =D8*E8 | I8: =D8*F8
A9: layout/design | B9: seat | C9: 4 | D9: 0.1005 | E9: 0.5691 | F9: 1 | G9: 0.2845 | H9: =D9*E9 | I9: =D9*F9
A10: versioning/resizing/localization | B10: usage | C10: 4 | D10: 0.1005 | E10: 0.0889 | F10: 1 | G10: 0.0444 | H10: =D10*E10 | I10: =D10*F10
A11: brand compliance/review/approval | B11: enterprise platform | C11: 7 | D11: 0.1216 | E11: 0.5367 | F11: 0.966 | G11: 0.2683 | H11: =D11*E11 | I11: =D11*F11
A12: client/stakeholder communication | B12: none/competitor | C12: 6 | D12: 0.0783 | E12: 1 | F12: 0.8332 | G12: 0.5 | H12: =D12*E12 | I12: =D12*F12
A13: asset management/distribution | B13: enterprise platform | C13: 3 | D13: 0.0524 | E13: 1 | F13: 1 | G13: 0.5473 | H13: =D13*E13 | I13: =D13*F13
A14: other: management/admin/physical | B14: none/competitor | C14: 6 | D14: 0.0408 | E14: 0.34 | F14: 1 | G14: 0.2793 | H14: =D14*E14 | I14: =D14*F14
A16: Share of highly exposed task weight by monetization model (formulas)
A17: monetization | B17: human-rated share | C17: GPT-4-rated share
A18: seat | B18: =SUMIF($B$6:$B$14,A18,$H$6:$H$14)/SUM($H$6:$H$14) | C18: =SUMIF($B$6:$B$14,A18,$I$6:$I$14)/SUM($I$6:$I$14)
A19: usage | B19: =SUMIF($B$6:$B$14,A19,$H$6:$H$14)/SUM($H$6:$H$14) | C19: =SUMIF($B$6:$B$14,A19,$I$6:$I$14)/SUM($I$6:$I$14)
A20: enterprise platform | B20: =SUMIF($B$6:$B$14,A20,$H$6:$H$14)/SUM($H$6:$H$14) | C20: =SUMIF($B$6:$B$14,A20,$I$6:$I$14)/SUM($I$6:$I$14)
A21: none/competitor | B21: =SUMIF($B$6:$B$14,A21,$H$6:$H$14)/SUM($H$6:$H$14) | C21: =SUMIF($B$6:$B$14,A21,$I$6:$I$14)/SUM($I$6:$I$14)
A23: Scheme: All 6 occupations incl. 11-2021 and 13-1161
A24: stage | B24: monetization | C24: n_tasks | D24: stage_weight_share | E24: share_highly_exposed_human | F24: share_highly_exposed_gpt4 | G24: mean_beta_human | H24: exposed_weight_human (formula) | I24: exposed_weight_gpt4 (formula)
A25: ideation/concepting | B25: seat | C25: 10 | D25: 0.0494 | E25: 1 | F25: 1 | G25: 0.5095 | H25: =D25*E25 | I25: =D25*F25
A26: asset generation | B26: seat | C26: 13 | D26: 0.05 | E26: 0.9813 | F26: 1 | G26: 0.4906 | H26: =D26*E26 | I26: =D26*F26
A27: editing/retouching/compositing | B27: seat | C27: 16 | D27: 0.0152 | E27: 0.8765 | F27: 1 | G27: 0.5309 | H27: =D27*E27 | I27: =D27*F27
A28: layout/design | B28: seat | C28: 4 | D28: 0.0228 | E28: 0.5691 | F28: 1 | G28: 0.2845 | H28: =D28*E28 | I28: =D28*F28
A29: versioning/resizing/localization | B29: usage | C29: 4 | D29: 0.0228 | E29: 0.0889 | F29: 1 | G29: 0.0444 | H29: =D29*E29 | I29: =D29*F29
A30: brand compliance/review/approval | B30: enterprise platform | C30: 7 | D30: 0.0275 | E30: 0.5367 | F30: 0.966 | G30: 0.2683 | H30: =D30*E30 | I30: =D30*F30
A31: client/stakeholder communication | B31: none/competitor | C31: 6 | D31: 0.0177 | E31: 1 | F31: 0.8332 | G31: 0.5 | H31: =D31*E31 | I31: =D31*F31
A32: asset management/distribution | B32: enterprise platform | C32: 3 | D32: 0.0119 | E32: 1 | F32: 1 | G32: 0.5473 | H32: =D32*E32 | I32: =D32*F32
A33: other: marketing analytics & insight | B33: enterprise platform | C33: 16 | D33: 0.5914 | E33: 0.9273 | F33: 1 | G33: 0.5727 | H33: =D33*E33 | I33: =D33*F33
A34: other: marketing strategy & planning | B34: none/competitor | C34: 13 | D34: 0.1393 | E34: 1 | F34: 1 | G34: 0.6538 | H34: =D34*E34 | I34: =D34*F34
A35: other: management/admin/physical | B35: none/competitor | C35: 10 | D35: 0.0521 | E35: 0.6772 | F35: 0.7944 | G35: 0.4608 | H35: =D35*E35 | I35: =D35*F35
A37: Share of highly exposed task weight by monetization model (formulas)
A38: monetization | B38: human-rated share | C38: GPT-4-rated share
A39: seat | B39: =SUMIF($B$25:$B$35,A39,$H$25:$H$35)/SUM($H$25:$H$35) | C39: =SUMIF($B$25:$B$35,A39,$I$25:$I$35)/SUM($I$25:$I$35)
A40: usage | B40: =SUMIF($B$25:$B$35,A40,$H$25:$H$35)/SUM($H$25:$H$35) | C40: =SUMIF($B$25:$B$35,A40,$I$25:$I$35)/SUM($I$25:$I$35)
A41: enterprise platform | B41: =SUMIF($B$25:$B$35,A41,$H$25:$H$35)/SUM($H$25:$H$35) | C41: =SUMIF($B$25:$B$35,A41,$I$25:$I$35)/SUM($I$25:$I$35)
A42: none/competitor | B42: =SUMIF($B$25:$B$35,A42,$H$25:$H$35)/SUM($H$25:$H$35) | C42: =SUMIF($B$25:$B$35,A42,$I$25:$I$35)/SUM($I$25:$I$35)
A44: Occupation-level exposure scores (Eloundou human/GPT-4 alpha-beta-gamma with percentiles; AIOE overall / image generation / language modeling)
A45: onet_soc | B45: title | C45: dv_rating_alpha | D45: dv_rating_alpha_pctile | E45: dv_rating_beta | F45: dv_rating_beta_pctile | G45: dv_rating_gamma | H45: dv_rating_gamma_pctile | I45: human_rating_alpha | J45: human_rating_alpha_pctile | K45: human_rating_beta | L45: human_rating_beta_pctile | M45: human_rating_gamma | N45: human_rating_gamma_pctile | O45: AIOE | P45: AIOE_pctile | Q45: AIOE_image_generation | R45: AIOE_image_generation_pctile | S45: AIOE_language_modeling | T45: AIOE_language_modeling_pctile | U45: eloundou_source | V45: aioe_source
A46: 11-2021.00 | B46: Marketing Managers | C46: 0.062 | D46: 33.532 | E46: 0.5 | F46: 75.027 | G46: 0.938 | H46: 84.074 | I46: 0.219 | J46: 71.939 | K46: 0.578 | L46: 89.816 | M46: 0.938 | N46: 96.046 | O46: 1.315 | P46: 89.018 | Q46: 1.61 | R46: 95.349 | S46: 1.204 | T46: 83.333 | U46: openai/GPTs-are-GPTs data/occ_level.csv (commit 2025-10-03/04); percentile among 923 O*NET-SOC occupations | V46: AIOE-Data/AIOE (last commit 2024-06-03; AIOE 2021 SMJ; IG/LM extensions added 2023); percentile among 774 SOC occupations
A47: 13-1161.00 | B47: Market Research Analysts and Marketing Specialists | C47: 0 | D47: 10.022 | E47: 0.5 | F47: 75.027 | G47: 1 | H47: 95.395 | I47: 0.231 | J47: 74.215 | K47: 0.577 | L47: 89.653 | M47: 0.923 | N47: 94.8 | O47: 1.427 | P47: 97.416 | Q47: 1.396 | R47: 92.119 | S47: 1.356 | T47: 90.439 | U47: openai/GPTs-are-GPTs data/occ_level.csv (commit 2025-10-03/04); percentile among 923 O*NET-SOC occupations | V47: AIOE-Data/AIOE (last commit 2024-06-03; AIOE 2021 SMJ; IG/LM extensions added 2023); percentile among 774 SOC occupations
A48: 27-1011.00 | B48: Art Directors | C48: 0.069 | D48: 36.728 | E48: 0.5 | F48: 75.027 | G48: 0.931 | H48: 83.424 | I48: 0.069 | J48: 39.166 | K48: 0.431 | L48: 69.502 | M48: 0.793 | N48: 83.044 | O48: 1.023 | P48: 75.323 | Q48: 2.249 | R48: 99.612 | S48: 0.727 | T48: 69.509 | U48: openai/GPTs-are-GPTs data/occ_level.csv (commit 2025-10-03/04); percentile among 923 O*NET-SOC occupations | V48: AIOE-Data/AIOE (last commit 2024-06-03; AIOE 2021 SMJ; IG/LM extensions added 2023); percentile among 774 SOC occupations
A49: 27-1014.00 | B49: Special Effects Artists and Animators | C49: 0.05 | D49: 28.277 | E49: 0.525 | F49: 80.336 | G49: 1 | H49: 95.395 | I49: 0.05 | J49: 34.886 | K49: 0.475 | L49: 75.515 | M49: 0.9 | N49: 93.337 | O49: 0.706 | P49: 66.537 | Q49: 1.845 | R49: 97.804 | S49: 0.432 | T49: 61.757 | U49: openai/GPTs-are-GPTs data/occ_level.csv (commit 2025-10-03/04); percentile among 923 O*NET-SOC occupations | V49: AIOE-Data/AIOE (last commit 2024-06-03; AIOE 2021 SMJ; IG/LM extensions added 2023); percentile among 774 SOC occupations
A50: 27-1024.00 | B50: Graphic Designers | C50: 0 | D50: 10.022 | E50: 0.5 | F50: 75.027 | G50: 1 | H50: 95.395 | I50: 0 | J50: 14.68 | K50: 0.411 | L50: 66.576 | M50: 0.821 | N50: 85.97 | O50: 0.716 | P50: 67.054 | Q50: 1.917 | R50: 98.708 | S50: 0.527 | T50: 63.566 | U50: openai/GPTs-are-GPTs data/occ_level.csv (commit 2025-10-03/04); percentile among 923 O*NET-SOC occupations | V50: AIOE-Data/AIOE (last commit 2024-06-03; AIOE 2021 SMJ; IG/LM extensions added 2023); percentile among 774 SOC occupations
A51: 27-4032.00 | B51: Film and Video Editors | C51: 0.111 | D51: 55.471 | E51: 0.528 | F51: 81.148 | G51: 0.944 | H51: 85.103 | I51: 0.139 | J51: 54.713 | K51: 0.472 | L51: 74.973 | M51: 0.806 | N51: 84.182 | O51: 0.986 | P51: 73.902 | Q51: 1.97 | R51: 98.837 | S51: 0.657 | T51: 67.7 | U51: openai/GPTs-are-GPTs data/occ_level.csv (commit 2025-10-03/04); percentile among 923 O*NET-SOC occupations | V51: AIOE-Data/AIOE (last commit 2024-06-03; AIOE 2021 SMJ; IG/LM extensions added 2023); percentile among 774 SOC occupations

Sheet CallNLP
A1: WS4: earnings-call analyst-question analysis and forward P/E (blue = counted/sourced input; black = formula)
A2: 13 of 15 calls from full transcripts (GitHub mirrors); FY25 Q2 and FY26 Q3 reconstructed from search snippets (partial coverage, LOW confidence). Topic labels hand-reviewed (72% agreement with keyword rules).
A4: A. Analyst question counts by topic, fear index (formula) and forward P/E (formula)
A5: call | B5: call_date | C5: n_questions | D5: n_ai_disruption | E5: n_seats_pricing | F5: n_ai_monetization | G5: n_dx | H5: n_margins | I5: n_leadership | J5: n_macro_other | K5: fear_index_strict (f) | L5: fear_index_broad_src | M5: coverage | N5: price_next_day_close | O5: guidance_fy | P5: guide_eps_low | Q5: guide_eps_high | R5: guide_eps_mid (f) | S5: forward_pe (f) | T5: guidance_basis | U5: guidance_url
A6: FY23_Q1 | B6: 2023-03-15 | C6: 10 | D6: 1 | E6: 2 | F6: 1 | G6: 2 | H6: 0 | I6: 0 | J6: 4 | K6: =(D6+E6)/C6 | L6: 0.5 | M6: full transcript | N6: 353.29 | O6: FY23 | P6: 15.3 | Q6: 15.6 | R6: =AVERAGE(P6:Q6) | S6: =N6/R6 | T6: transcript (CFO prepared remarks) | U6: https://www.sec.gov/Archives/edgar/data/796343/000079634323000044/adbeex991q123.htm
A7: FY23_Q2 | B7: 2023-06-15 | C7: 10 | D7: 1 | E7: 0 | F7: 4 | G7: 1 | H7: 1 | I7: 0 | J7: 3 | K7: =(D7+E7)/C7 | L7: 0.1 | M7: full transcript | N7: 495.18 | O7: FY23 | P7: 15.65 | Q7: 15.75 | R7: =AVERAGE(P7:Q7) | S7: =N7/R7 | T7: transcript (CFO prepared remarks) | U7: https://www.sec.gov/Archives/edgar/data/796343/000079634323000133/adbeex991q223.htm
A8: FY23_Q3 | B8: 2023-09-14 | C8: 11 | D8: 0 | E8: 1 | F8: 5 | G8: 1 | H8: 1 | I8: 0 | J8: 3 | K8: =(D8+E8)/C8 | L8: 0.091 | M8: full transcript | N8: 528.89 | O8: FY23 | P8: 15.9 | Q8: 15.95 | R8: =AVERAGE(P8:Q8) | S8: =N8/R8 | T8: implied: 9M actual non-GAAP EPS 11.80 (3.80+3.91+4.09) + Q4 target 4.10-4.15 from transcript | U8: https://www.sec.gov/Archives/edgar/data/796343/000079634323000198/adbeex991q323.htm
A9: FY23_Q4 | B9: 2023-12-13 | C9: 10 | D9: 1 | E9: 3 | F9: 2 | G9: 1 | H9: 0 | I9: 0 | J9: 3 | K9: =(D9+E9)/C9 | L9: 0.4 | M9: full transcript | N9: 584.64 | O9: FY24 | P9: 17.6 | Q9: 18 | R9: =AVERAGE(P9:Q9) | S9: =N9/R9 | T9: transcript (CFO prepared remarks) | U9: https://www.sec.gov/Archives/edgar/data/796343/000079634323000252/adbeex991q423.htm
A10: FY24_Q1 | B10: 2024-03-14 | C10: 10 | D10: 3 | E10: 4 | F10: 1 | G10: 0 | H10: 1 | I10: 0 | J10: 1 | K10: =(D10+E10)/C10 | L10: 0.7 | M10: full transcript | N10: 492.46 | O10: FY24 | P10: 17.6 | Q10: 18 | R10: =AVERAGE(P10:Q10) | S10: =N10/R10 | T10: not updated on call (Q&A: analyst asked management to affirm; prior range carried) | U10: https://www.sec.gov/Archives/edgar/data/796343/000079634324000057/adbeex991q124.htm
A11: FY24_Q2 | B11: 2024-06-13 | C11: 13 | D11: 0 | E11: 5 | F11: 4 | G11: 2 | H11: 0 | I11: 0 | J11: 2 | K11: =(D11+E11)/C11 | L11: 0.385 | M11: full transcript | N11: 525.31 | O11: FY24 | P11: 18 | Q11: 18.2 | R11: =AVERAGE(P11:Q11) | S11: =N11/R11 | T11: transcript (CFO prepared remarks) | U11: https://www.sec.gov/Archives/edgar/data/796343/000079634324000140/adbeex991q224.htm
A12: FY24_Q3 | B12: 2024-09-12 | C12: 8 | D12: 0 | E12: 2 | F12: 2 | G12: 1 | H12: 1 | I12: 0 | J12: 2 | K12: =(D12+E12)/C12 | L12: 0.625 | M12: full transcript | N12: 536.87 | O12: FY24 | P12: 18.24 | Q12: 18.29 | R12: =AVERAGE(P12:Q12) | S12: =N12/R12 | T12: implied: 9M actual 13.61 (4.48+4.48+4.65) + Q4 target 4.63-4.68 from transcript | U12: https://www.sec.gov/Archives/edgar/data/796343/000079634324000200/adbeex991q324.htm
A13: FY24_Q4 | B13: 2024-12-11 | C13: 10 | D13: 0 | E13: 4 | F13: 4 | G13: 0 | H13: 0 | I13: 0 | J13: 2 | K13: =(D13+E13)/C13 | L13: 0.6 | M13: full transcript | N13: 474.63 | O13: FY25 | P13: 20.2 | Q13: 20.5 | R13: =AVERAGE(P13:Q13) | S13: =N13/R13 | T13: transcript (CFO prepared remarks) | U13: https://www.sec.gov/Archives/edgar/data/796343/000079634324000250/adbeex991q424.htm
A14: FY25_Q1 | B14: 2025-03-12 | C14: 13 | D14: 1 | E14: 0 | F14: 5 | G14: 0 | H14: 2 | I14: 0 | J14: 5 | K14: =(D14+E14)/C14 | L14: 0.231 | M14: full transcript | N14: 377.84 | O14: FY25 | P14: 20.2 | Q14: 20.5 | R14: =AVERAGE(P14:Q14) | S14: =N14/R14 | T14: transcript: 'reaffirm our fiscal '25 targets' | U14: https://www.sec.gov/Archives/edgar/data/796343/000079634325000052/adbeex991q125.htm
A15: FY25_Q2 | B15: 2025-06-12 | C15: 2 | D15: 1 | E15: 1 | F15: 0 | G15: 0 | H15: 0 | I15: 0 | J15: 0 | K15: =(D15+E15)/C15 | L15: 1 | M15: partial coverage: Alex Zukin (Wolfe), Brent Thill (Jefferies | N15: 391.68 | O15: FY25 | P15: 20.5 | Q15: 20.7 | R15: =AVERAGE(P15:Q15) | S15: =N15/R15 | T15: WebSearch snippet of Q2 FY25 press release (8-K ex99.1); transcript not available | U15: https://www.sec.gov/Archives/edgar/data/796343/000079634325000064/adbeex991q225.htm
A16: FY25_Q3 | B16: 2025-09-11 | C16: 10 | D16: 2 | E16: 3 | F16: 2 | G16: 2 | H16: 1 | I16: 0 | J16: 0 | K16: =(D16+E16)/C16 | L16: 0.5 | M16: full transcript | N16: 349.36 | O16: FY25 | P16: 20.8 | Q16: 20.85 | R16: =AVERAGE(P16:Q16) | S16: =N16/R16 | T16: transcript (CFO prepared remarks) | U16: https://www.sec.gov/Archives/edgar/data/796343/000079634325000102/adbeex991q325.htm
A17: FY25_Q4 | B17: 2025-12-10 | C17: 8 | D17: 0 | E17: 3 | F17: 3 | G17: 2 | H17: 0 | I17: 0 | J17: 0 | K17: =(D17+E17)/C17 | L17: 0.375 | M17: full transcript | N17: 350.43 | O17: FY26 | P17: 23.3 | Q17: 23.5 | R17: =AVERAGE(P17:Q17) | S17: =N17/R17 | T17: transcript (CFO prepared remarks) | U17: https://www.sec.gov/Archives/edgar/data/796343/000079634325000135/adbeex991q425.htm
... A20: FY26_Q3 | B20: 2026-09-10 | C20: 6 | D20: 1 | E20: 2 | F20: 2 | G20: 0 | H20: 0 | I20: 0 | J20: 1 | K20: =(D20+E20)/C20 | L20: 0.833 | M20: partial coverage: Michael Turrin (Wells Fargo), Saket Kalia | N20: 252.23 | O20: FY26 | P20: 24.45 | Q20: 24.5 | R20: =AVERAGE(P20:Q20) | S20: =N20/R20 | T20: WebSearch snippet of Q3 FY26 press release (8-K ex99.1); transcript not available | U20: https://www.sec.gov/Archives/edgar/data/0000796343/000079634326000147/adbeex991q326.htm
A22: Correlation(fear index strict, forward P/E), all 15 calls (formula) | B22: =CORREL(K6:K20,S6:S20)
A23: Mean fear index FY23 calls (formula) | B23: =AVERAGE(K6:K9)
A24: Mean fear index FY26 calls (formula) | B24: =AVERAGE(K18:K20)
A25: Forward P/E change, first to last call (formula) | B25: =S20/S6-1
A27: B. Management vocabulary per 10k words: seat vs usage terms (hits in blue; rates and ratio are formulas)
A28: call | B28: date | C28: mgmt_words | D28: seat_hits | E28: usage_hits | F28: seat_per_10k (f) | G28: usage_per_10k (f) | H28: usage_minus_seat (f) | I28: usage_to_seat_ratio (f) | J28: detail
A29: FY23_Q1 | B29: 2023-03-15 | C29: 7754 | D29: 2 | E29: 5 | F29: =D29/C29*10000 | G29: =E29/C29*10000 | H29: =G29-F29 | I29: =IF(D29=0,"n/a",E29/D29) | J29: {"seat": 1, "subscribers": 1, "consumption": 1, "usage": 2, "apis?": 2}
A30: FY23_Q2 | B30: 2023-06-15 | C30: 8134 | D30: 3 | E30: 8 | F30: =D30/C30*10000 | G30: =E30/C30*10000 | H30: =G30-F30 | I30: =IF(D30=0,"n/a",E30/D30) | J30: {"seat": 2, "subscribers": 1, "credit": 2, "consumption": 1, "usage": 2, "generations": 2, "apis?": 1}
A31: FY23_Q3 | B31: 2023-09-14 | C31: 8117 | D31: 1 | E31: 27 | F31: =D31/C31*10000 | G31: =E31/C31*10000 | H31: =G31-F31 | I31: =IF(D31=0,"n/a",E31/D31) | J31: {"subscribers": 1, "credit": 3, "credits": 11, "consumption": 1, "usage": 5, "apis?": 7}
A32: FY23_Q4 | B32: 2023-12-13 | C32: 8304 | D32: 1 | E32: 23 | F32: =D32/C32*10000 | G32: =E32/C32*10000 | H32: =G32-F32 | I32: =IF(D32=0,"n/a",E32/D32) | J32: {"subscriber": 1, "credits": 2, "consumption": 1, "usage": 15, "generations": 4, "apis?": 1}
A33: FY24_Q1 | B33: 2024-03-14 | C33: 9154 | D33: 4 | E33: 33 | F33: =D33/C33*10000 | G33: =E33/C33*10000 | H33: =G33-F33 | I33: =IF(D33=0,"n/a",E33/D33) | J33: {"seats": 2, "subscribers": 2, "credit": 1, "credits": 2, "consumption": 1, "usage": 8, "generations": 1, "firefly services": 14, "apis?": 6}
A34: FY24_Q2 | B34: 2024-06-13 | C34: 8378 | D34: 1 | E34: 34 | F34: =D34/C34*10000 | G34: =E34/C34*10000 | H34: =G34-F34 | I34: =IF(D34=0,"n/a",E34/D34) | J34: {"seat": 1, "credit": 1, "consumption": 1, "usage": 12, "generations": 5, "firefly services": 12, "apis?": 2, "outcomes": 1}
A35: FY24_Q3 | B35: 2024-09-12 | C35: 7705 | D35: 1 | E35: 32 | F35: =D35/C35*10000 | G35: =E35/C35*10000 | H35: =G35-F35 | I35: =IF(D35=0,"n/a",E35/D35) | J35: {"subscribers": 1, "credits": 4, "consumption": 6, "usage": 7, "generations": 4, "firefly services": 6, "apis?": 5}
A36: FY24_Q4 | B36: 2024-12-11 | C36: 7938 | D36: 1 | E36: 28 | F36: =D36/C36*10000 | G36: =E36/C36*10000 | H36: =G36-F36 | I36: =IF(D36=0,"n/a",E36/D36) | J36: {"subscribers": 1, "credits": 1, "consumption": 5, "usage": 3, "generations": 4, "firefly services": 13, "apis?": 2}
A37: FY25_Q1 | B37: 2025-03-12 | C37: 8490 | D37: 3 | E37: 26 | F37: =D37/C37*10000 | G37: =E37/C37*10000 | H37: =G37-F37 | I37: =IF(D37=0,"n/a",E37/D37) | J37: {"seats": 2, "subscribers": 1, "credits": 1, "consumption": 4, "usage": 8, "generations": 3, "firefly services": 9, "outcomes": 1}
A38: FY25_Q3 | B38: 2025-09-11 | C38: 8168 | D38: 6 | E38: 31 | F38: =D38/C38*10000 | G38: =E38/C38*10000 | H38: =G38-F38 | I38: =IF(D38=0,"n/a",E38/D38) | J38: {"seat": 5, "subscribers": 1, "consumption": 5, "usage": 10, "generations": 4, "firefly services": 11, "outcomes": 1}
A39: FY25_Q4 | B39: 2025-12-10 | C39: 7809 | D39: 2 | E39: 42 | F39: =D39/C39*10000 | G39: =E39/C39*10000 | H39: =G39-F39 | I39: =IF(D39=0,"n/a",E39/D39) | J39: {"seat": 1, "subscribers": 1, "credit": 6, "credits": 12, "consumption": 5, "usage": 6, "firefly services": 10, "apis?": 2, "outcome": 1}
A40: FY26_Q1 | B40: 2026-03-12 | C40: 7638 | D40: 2 | E40: 40 | F40: =D40/C40*10000 | G40: =E40/C40*10000 | H40: =G40-F40 | I40: =IF(D40=0,"n/a",E40/D40) | J40: {"license": 2, "credit": 8, "credits": 2, "consumption": 5, "usage": 12, "generations": 3, "firefly services": 4, "apis?": 2, "outcome": 2, "outcomes": 2}
A41: FY26_Q2 | B41: 2026-06-11 | C41: 4804 | D41: 1 | E41: 11 | F41: =D41/C41*10000 | G41: =E41/C41*10000 | H41: =G41-F41 | I41: =IF(D41=0,"n/a",E41/D41) | J41: {"subscribers": 1, "credit": 2, "consumption": 2, "usage": 7}

Sheet Trends_Competitors
A1: WS5: competitor growth vs Adobe (blue = sourced input; black = formula)
A3: Source: research/ws5_trends_competitors/data/growth_comparison.csv; each row's primary URL is in the Sources tab (WS5). Google Trends: UNAVAILABLE (host blocked); manual export kit in ws5 data/.
A4: entity | B4: metric | C4: period | D4: period_end | E4: value_musd | F4: prior_value_musd | G4: yoy_growth_calc | H4: incremental_calc | I4: annualized_incremental_calc | J4: basis | K4: note
A5: Figma | B5: revenue | C5: FY2023 | D5: 2023-12-31 | E5: 504 | J5: reported | K5: S-1
A6: Figma | B6: revenue | C6: FY2024 | D6: 2024-12-31 | E6: 749 | F6: 504 | G6: =E6/F6-1 | H6: =E6-F6 | I6: =H6*1 | J6: reported | K6: S-1
A7: Figma | B7: revenue | C7: FY2025 | D7: 2025-12-31 | E7: 1056 | F7: 749 | G7: =E7/F7-1 | H7: =E7-F7 | I7: =H7*1 | J7: reported | K7: 8-K 2026-02-18
A8: Figma | B8: revenue guide (midpoint) | C8: FY2026 | D8: 2026-12-31 | E8: 1465 | F8: 1056 | G8: =E8/F8-1 | H8: =E8-F8 | I8: =H8*1 | J8: guidance | K8: 8-K 2026-08-05 ($1.463-1.467B)
A9: Figma | B9: revenue | C9: Q1 2025 | D9: 2025-03-31 | E9: 228.2 | F9: 156.2 | G9: =E9/F9-1 | H9: =E9-F9 | I9: =H9*4 | J9: reported | K9: S-1
A10: Figma | B10: revenue | C10: Q2 2025 | D10: 2025-06-30 | E10: 249.6 | F10: 177 | G10: =E10/F10-1 | H10: =E10-F10 | I10: =H10*4 | J10: reported; prior derived | K10: prior = 249.6/1.41
A11: Figma | B11: revenue | C11: Q3 2025 | D11: 2025-09-30 | E11: 274.2 | F11: 198.7 | G11: =E11/F11-1 | H11: =E11-F11 | I11: =H11*4 | J11: reported; prior derived | K11: prior = 274.2/1.38
A12: Figma | B12: revenue | C12: Q4 2025 | D12: 2025-12-31 | E12: 303.8 | F12: 217 | G12: =E12/F12-1 | H12: =E12-F12 | I12: =H12*4 | J12: reported; prior derived | K12: prior = 303.8/1.40
A13: Figma | B13: revenue | C13: Q1 2026 | D13: 2026-03-31 | E13: 333.4 | F13: 228.2 | G13: =E13/F13-1 | H13: =E13-F13 | I13: =H13*4 | J13: reported | K13: 8-K 2026-05-14
A14: Figma | B14: revenue | C14: Q2 2026 | D14: 2026-06-30 | E14: 370.1 | F14: 249.6 | G14: =E14/F14-1 | H14: =E14-F14 | I14: =H14*4 | J14: reported | K14: 8-K 2026-08-05 (LATEST)
A15: Canva | B15: ARR | C15: CY2023 | D15: 2023-12-31 | E15: 1700 | J15: ESTIMATE (Sacra) | K15: private company
A16: Canva | B16: ARR | C16: CY2024 | D16: 2024-12-31 | E16: 2800 | F16: 1700 | G16: =E16/F16-1 | H16: =E16-F16 | I16: =H16*1 | J16: ESTIMATE (Sacra) | K16: company-stated figures in H2-2024 were $2.3-2.55B so 2024 growth is uncertain (roughly 35-65%)
A17: Canva | B17: ARR | C17: CY2025 | D17: 2025-12-31 | E17: 4000 | F17: 2800 | G17: =E17/F17-1 | H17: =E17-F17 | I17: =H17*1 | J17: company-stated end value; Sacra YoY | K17: $4B incl. ~$500M from >25-seat business customers
A18: Canva | B18: ARR 2-yr CAGR | C18: CY2023-CY2025 | D18: 2025-12-31 | E18: 4000 | F18: 1700 | G18: =E18/F18-1 | H18: =E18-F18 | I18: =H18*1 | J18: mixed | K18: (4000/1700)^0.5 - 1
A19: Canva | B19: revenue | C19: Q2 2026 | D19: 2026-06-30 | E19: 921.9 | F19: 736.3 | G19: =E19/F19-1 | H19: =E19-F19 | I19: =H19*4 | J19: reported via press; prior derived | K19: prior = 921.9/1.252; Q2-2026 investor update as reported Aug 2026 (LATEST)
A20: Canva | B20: revenue growth guide | C20: CY2026 | D20: 2026-12-31 | G20: 0.2 | J20: guidance (reported) | K20: cut from 30% in Aug 2026 on AI serving costs
A21: Midjourney | B21: revenue | C21: CY2024 | D21: 2024-12-31 | E21: 300 | F21: 200 | G21: =E21/F21-1 | H21: =E21-F21 | I21: =H21*1 | J21: ESTIMATE (Sacra/GetLatka)
A22: Midjourney | B22: revenue | C22: CY2025 | D22: 2025-12-31 | E22: 500 | F22: 300 | G22: =E22/F22-1 | H22: =E22-F22 | I22: =H22*1 | J22: ESTIMATE (Sacra/GetLatka)
A23: Adobe | B23: Digital Media revenue | C23: FY2023 | D23: 2023-12-01 | E23: 14216 | J23: reported | K23: 8-K 2023-12-13
A24: Adobe | B24: Digital Media revenue | C24: FY2024 | D24: 2024-11-29 | E24: 15860 | F24: 14216 | G24: =E24/F24-1 | H24: =E24-F24 | I24: =H24*1 | J24: reported | K24: 8-K 2024-12-11 (reported as 12%)
A25: Adobe | B25: Digital Media revenue | C25: FY2025 | D25: 2025-11-28 | E25: 17650 | F25: 15860 | G25: =E25/F25-1 | H25: =E25-F25 | I25: =H25*1 | J25: reported | K25: 8-K 2025-12-10 (reported as 11%)
A26: Adobe | B26: Creative revenue | C26: FY2023 | D26: 2023-12-01 | E26: 11520 | G26: 0.1 | J26: reported | K26: 8-K 2023-12-13
A27: Adobe | B27: Creative revenue | C27: FY2024 | D27: 2024-11-29 | E27: 12680 | F27: 11520 | G27: =E27/F27-1 | H27: =E27-F27 | I27: =H27*1 | J27: derived (DM minus DC) | K27: Q4 FY24 Creative $3.30B +10%
A28: Adobe | B28: Creative revenue | C28: FY2025 | D28: 2025-11-28 | J28: UNAVAILABLE | K28: Adobe no longer discloses Creative vs Document Cloud revenue split (customer-group reporting from FY25)
A29: Adobe | B29: Document Cloud revenue | C29: FY2023 | D29: 2023-12-01 | E29: 2700 | G29: 0.13 | J29: reported | K29: 8-K 2023-12-13
A30: Adobe | B30: Document Cloud revenue | C30: FY2024 | D30: 2024-11-29 | E30: 3180 | F30: 2700 | G30: =E30/F30-1 | H30: =E30-F30 | I30: =H30*1 | J30: reported | K30: 8-K 2024-12-11 (reported as 18%)
A31: Adobe | B31: Document Cloud revenue | C31: FY2025 | D31: 2025-11-28 | J31: UNAVAILABLE | K31: see Creative FY2025 note
A32: Adobe | B32: total revenue | C32: FY2023 | D32: 2023-12-01 | E32: 19410 | J32: reported
A33: Adobe | B33: total revenue | C33: FY2024 | D33: 2024-11-29 | E33: 21510 | F33: 19410 | G33: =E33/F33-1 | H33: =E33-F33 | I33: =H33*1 | J33: reported | K33: reported as 11%
A34: Adobe | B34: total revenue | C34: FY2025 | D34: 2025-11-28 | E34: 23770 | F34: 21510 | G34: =E34/F34-1 | H34: =E34-F34 | I34: =H34*1 | J34: reported | K34: reported as 11%
A35: Adobe | B35: total revenue guide (midpoint) | C35: FY2026 | D35: 2026-11-27 | E35: 26000 | F35: 23770 | G35: =E35/F35-1 | H35: =E35-F35 | I35: =H35*1 | J35: guidance | K35: $25.9-26.1B given 2025-12-10
A36: Adobe | B36: C&MP subscription revenue | C36: FY2025 | D36: 2025-11-28 | J36: UNAVAILABLE | K36: full-year FY25 customer-group totals not surfaced by WebSearch; Q4 FY25 quarter used instead
A37: Adobe | B37: C&MP subscription revenue | C37: Q4 FY2025 | D37: 2025-11-28 | E37: 4250 | G37: 0.11 | J37: reported | K37: 8-K 2025-12-10
A38: Adobe | B38: BP&C subscription revenue | C38: Q4 FY2025 | D38: 2025-11-28 | E38: 1700 | G38: 0.15 | J38: reported | K38: 8-K 2025-12-10
A39: Adobe | B39: C&MP subscription revenue | C39: Q3 FY2026 | D39: 2026-08-28 | E39: 4651 | F39: 4117 | G39: =E39/F39-1 | H39: =E39-F39 | I39: =H39*4 | J39: reported (10-Q) | K39: orchestrator starting facts; +12% cc (LATEST)
A40: Adobe | B40: BP&C subscription revenue | C40: Q3 FY2026 | D40: 2026-08-28 | E40: 1905 | F40: 1648 | G40: =E40/F40-1 | H40: =E40-F40 | I40: =H40*4 | J40: reported (10-Q) | K40: orchestrator starting facts; +15% cc (LATEST)
A41: Adobe | B41: total revenue | C41: Q3 FY2026 | D41: 2026-08-28 | E41: 6760 | F41: 5988 | G41: =E41/F41-1 | H41: =E41-F41 | I41: =H41*4 | J41: reported (10-Q) | K41: prior derived = 6760/1.129 (LATEST)
A42: Adobe | B42: total ending ARR | C42: Q3 FY2026 | D42: 2026-08-28 | E42: 27500 | F42: 24730 | G42: =E42/F42-1 | H42: =E42-F42 | I42: =H42*4 | J42: reported (10-Q) | K42: prior derived = 27500/1.112; FY26 ARR definition includes Experience Cloud + Semrush
A43: Adobe | B43: C&MP subscription revenue guide (midpoint) | C43: FY2026 | D43: 2026-11-27 | E43: 18257 | J43: guidance | K43: $18.242-18.272B
A44: Adobe | B44: BP&C subscription revenue guide (midpoint) | C44: FY2026 | D44: 2026-11-27 | E44: 7480 | J44: guidance | K44: $7.47-7.49B
A46: Share-of-pool calc (latest annualized run-rates; formulas)
A47: entity | B47: run_rate_musd (latest quarter x4 / ARR) | C47: annualized_increment_musd | D47: share_of_stock | E47: share_of_increment
A48: Adobe C&MP (Q3 FY26 x4) | B48: 18604 | C48: 2136 | D48: =B48/SUM($B$48:$B$50) | E48: =C48/SUM($C$48:$C$50)
A49: Figma (Q2'26 x4) | B49: 1480.4 | C49: 482 | D49: =B49/SUM($B$48:$B$50) | E49: =C49/SUM($C$48:$C$50)
A50: Canva (Q2'26 revenue x4) | B50: 3687.6 | C50: 742.4 | D50: =B50/SUM($B$48:$B$50) | E50: =C50/SUM($C$48:$C$50)
A51: Pool total | B51: =SUM(B48:B50) | C51: =SUM(C48:C50)
A52: Pool growth (increment / (stock - increment)) | B52: =C51/(B51-C51)

Sheet Triangulation
A1: Triangulation matrix: rows = contentions C1-C4 + concessions; columns = source types. Cell = mark + one-line finding + source number (see research/tri/sources_numbered.md).
A3: PENDING: research/tri/triangulation_matrix.csv not yet written

Sheet EPS_bridge
A1: ARR -> EPS bridge (blue = input assumption; black = formula). Each contention's EPS translation references the constant in B8.
A2: Constant: EPS per $100M ARR = 100 x incremental operating margin x (1 - non-GAAP tax rate) / diluted shares. Inputs sourced in Inputs tab / Sources tab.
A4: Input | B4: Value | C4: Unit | D4: Source / note
A5: Incremental ARR block (USD M) | B5: 100 | C5: USD M | D5: convention
A6: Incremental non-GAAP operating margin on new ARR | B6: 0.45 | C6: ratio | D6: Adobe FY26 target non-GAAP operating margin ~45.0% (Q3 FY26 8-K Ex.99.1, verified 2026-10-02); incremental assumed at run-rate margin; see 35% low case
A7: Non-GAAP tax rate | B7: 0.18 | C7: ratio | D7: Adobe FY26 target non-GAAP tax rate ~18.0% (Q3 FY26 8-K Ex.99.1, verified 2026-10-02)
A8: Diluted shares (M) | B8: 389 | C8: M | D8: Q4 FY26 target diluted share count ~389M (Q3 FY26 8-K Ex.99.1, verified 2026-10-02); FY26 full-year ~400M
A9: Low-case incremental margin | B9: 0.35 | C9: ratio | D9: sensitivity
A10: EPS per $100M ARR (base) | B10: =B5*B6*(1-B7)/B8
A11: EPS per $100M ARR (low-case margin) | B11: =B5*B9*(1-B7)/B8
A13: Contention / concession EPS translations (ARR inputs in blue from research/tri/eps_translations.csv; EPS = ARR/100 x constant)
A14: id | B14: item | C14: scenario | D14: arr_delta_musd | E14: eps_base (f) | F14: eps_low_margin (f) | G14: as_%_of_FY27_consensus_EPS (f) | H14: source_ref | I14: note
A15: FY27 consensus EPS (FactSet via prior research; VERIFY) | D15: 27.5
A16: C1-a | B16: Individual Creative Cloud tier (base $6.25B = 23% of ARR) shrinks | C16: -5%/yr | D16: -313 | E16: =D16/100*$B$10 | F16: =D16/100*$B$11 | G16: =E16/$D$15 | H16: c1_mix/data/eps_at_risk.csv | I16: base case individual = 50% of Creative ARR; Adobe does not disclose the split
A17: C1-b | B17: Individual Creative Cloud tier shrinks | C17: -10%/yr | D17: -625 | E17: =D17/100*$B$10 | F17: =D17/100*$B$11 | G17: =E17/$D$15 | H17: c1_mix/data/eps_at_risk.csv
A18: C1-c | B18: Individual Creative Cloud tier shrinks | C18: -20%/yr | D18: -1250 | E18: =D18/100*$B$10 | F18: =D18/100*$B$11 | G18: =E18/$D$15 | H18: c1_mix/data/eps_at_risk.csv
A19: C1-d | B19: Individual tier at 60% of Creative ARR ($7.5B) shrinks | C19: -10%/yr | D19: -750 | E19: =D19/100*$B$10 | F19: =D19/100*$B$11 | G19: =E19/$D$15 | H19: c1_mix/data/eps_at_risk.csv | I19: high-exposure sensitivity
A20: C3-a | B20: Subscription gross margin -1pt on ~$25.8B FY26 subscription revenue (ARR-equivalent at 45% margin) | C20: -1pt GM | D20: -573 | E20: =D20/100*$B$10 | F20: =D20/100*$B$11 | G20: =E20/$D$15 | H20: c3_economics/data/eps_ai_cost_sensitivity.csv | I20: -$258M operating income = -$0.54 EPS; entered as ARR-equivalent (-258/0.45) so the bridge constant applies
A21: C3-b | B21: Observed Q3 FY26 subscription GM -0.81pt YoY annualised | C21: observed | D21: -464 | E21: =D21/100*$B$10 | F21: =D21/100*$B$11 | G21: =E21/$D$15 | H21: c3_economics/data/eps_ai_cost_sensitivity.csv | I21: -$209M operating income = -$0.44 EPS
A22: C3-c | B22: AI-first ARR net adds (Q3 FY25 >$250M to Q3 FY26 >$650M; lower bounds) | C22: +$400M/yr | D22: 400 | E22: =D22/100*$B$10 | F22: =D22/100*$B$11 | G22: =E22/$D$15 | H22: c3_economics/data/ai_first_arr_series.csv | I22: offsets ~0.7pt of subscription GM
A23: C4-a | B23: Creative freemium MAU 100M -> 150M at $8 AI-first ARR per incremental MAU (descriptive ratio) | C23: +50M MAU | D23: 400 | E23: =D23/100*$B$10 | F23: =D23/100*$B$11 | G23: =E23/$D$15 | H23: c4_users/data/mau_to_arr_ratio.csv | I23: ratio = (650-250)/(100-50); NOT causal
A24: C4-b | B24: Creative freemium MAU 100M -> 200M at $8/MAU | C24: +100M MAU | D24: 800 | E24: =D24/100*$B$10 | F24: =D24/100*$B$11 | G24: =E24/$D$15 | H24: c4_users/data/mau_to_arr_ratio.csv
A25: CON-1a | B25: Seat compression: 3% of est. $8.5B teams/enterprise Creative Cloud ARR | C25: -3% seats | D25: -255 | E25: =D25/100*$B$10 | F25: =D25/100*$B$11 | G25: =E25/$D$15 | H25: concessions/data/concessions_eps.csv | I25: basis ESTIMATE
A26: CON-1b | B26: Seat compression: 5% of teams/enterprise Creative Cloud ARR | C26: -5% seats | D26: -425 | E26: =D26/100*$B$10 | F26: =D26/100*$B$11 | G26: =E26/$D$15 | H26: concessions/data/concessions_eps.csv
A27: CON-2a | B27: Adobe Stock erosion on ~$450M book | C27: -10% | D27: -45 | E27: =D27/100*$B$10 | F27: =D27/100*$B$11 | G27: =E27/$D$15 | H27: concessions/data/concessions_eps.csv | I27: current implied decline only ~4%
A28: CON-2b | B28: Adobe Stock erosion | C28: -20% | D28: -90 | E28: =D28/100*$B$10 | F28: =D28/100*$B$11 | G28: =E28/$D$15 | H28: concessions/data/concessions_eps.csv | I28: Shutterstock content revenue -17% Q2 2026 as the peer analogue
A29: CON-3a | B29: Individual-subscriber weakness: 3% of est. $7.0B individual CC ARR | C29: -3% | D29: -210 | E29: =D29/100*$B$10 | F29: =D29/100*$B$11 | G29: =E29/$D$15 | H29: concessions/data/concessions_eps.csv
A30: CON-3b | B30: Individual-subscriber weakness | C30: -5% | D30: -350 | E30: =D30/100*$B$10 | F30: =D30/100*$B$11 | G30: =E30/$D$15 | H30: concessions/data/concessions_eps.csv
A31: CON-3c | B31: Management-implied H2 FY26 organic net-new-ARR cut (10.2% target held while Semrush added ~$480M) | C31: mgmt-implied | D31: -480 | E31: =D31/100*$B$10 | F31: =D31/100*$B$11 | G31: =E31/$D$15 | H31: concessions/data/individual_subscriber_quotes.csv
A32: CON-sum-base | B32: All three concessions | C32: base sum | D32: -510 | E32: =D32/100*$B$10 | F32: =D32/100*$B$11 | G32: =E32/$D$15 | H32: concessions/data/concessions_eps.csv | I32: 3% seats + 10% Stock + 3% individual
A33: CON-sum-bear | B33: All three concessions | C33: bear sum | D33: -865 | E33: =D33/100*$B$10 | F33: =D33/100*$B$11 | G33: =E33/$D$15 | H33: concessions/data/concessions_eps.csv | I33: 5% seats + 20% Stock + 5% individual
A34: NNARR | B34: FY26 organic net new ARR vs FY25 ($2.14B vs $2.63B) | C34: -$490M | D34: -490 | E34: =D34/100*$B$10 | F34: =D34/100*$B$11 | G34: =E34/$D$15 | H34: concessions/data/net_new_arr_fy25_vs_fy26.csv | I34: run-rate shortfall; FY27 consensus $2.34B needs +9% re-acceleration
A35: C2-a | B35: PENDING Subagent B: enterprise content-stack ARR growth scenarios | C35: 8/12/16% | E35: =D35/100*$B$10 | F35: =D35/100*$B$11 | G35: =E35/$D$15 | H35: c2_content/data/eps_content_stack.csv | I35: filled on completion

Sheet Sources
A1: All workstream sources (concatenated from each ws*/sources.csv)
A3: workstream | B3: claim | C3: value | D3: url | E3: date_accessed | F3: notes
A4: ws1_price_volume | B4: Adobe Q3 FY26 revenue | C4: $6.76B, +13% reported / +12% cc | D4: https://www.sec.gov/Archives/edgar/data/0000796343/000079634326000147/adbeex991q326.htm | E4: 2026-10-02 | F4: retrieved via WebSearch snippet; page not fetchable from this environment
A5: ws1_price_volume | B5: Adobe Q3 FY26 C&MP subscription revenue | C5: $4,651M vs $4,117M (+13% / +12% cc) | D5: https://www.sec.gov/Archives/edgar/data/0000796343/000079634326000156/adbe-20260828.htm | E5: 2026-10-02 | F5: orchestrator starting facts (10-Q Q3 FY26); growth rates matched by WebSearch snippet of 8-K Ex 99.1
A6: ws1_price_volume | B6: Adobe Q3 FY26 BP&C subscription revenue | C6: $1,905M vs $1,648M (+16% / +15% cc) | D6: https://www.sec.gov/Archives/edgar/data/0000796343/000079634326000156/adbe-20260828.htm | E6: 2026-10-02 | F6: orchestrator starting facts (10-Q Q3 FY26); growth matched by WebSearch snippet
A7: ws1_price_volume | B7: Adobe Q3 FY26 total ending ARR | C7: $27.50B, +11.2% YoY; AI-first ARR >$650M (+150%) | D7: https://www.sec.gov/Archives/edgar/data/0000796343/000079634326000147/adbeex991q326.htm | E7: 2026-10-02 | F7: retrieved via WebSearch snippet; page not fetchable from this environment
A8: ws1_price_volume | B8: Adobe Q2 FY26 revenue / C&MP / BP&C | C8: $6.62B (+13%); C&MP $4.54B (+13% / +11% cc); BP&C $1.85B (+16% / +15% cc) | D8: https://www.sec.gov/Archives/edgar/data/796343/000079634326000109/adbeex991q226.htm | E8: 2026-10-02 | F8: retrieved via WebSearch snippet; page not fetchable from this environment
A9: ws1_price_volume | B9: Adobe Q2 FY26 ending ARR incl. Semrush | C9: $27.10B incl ~$480M Semrush; +12.5% vs $24.08B restated at FY26 rates | D9: https://www.sec.gov/Archives/edgar/data/0000796343/000079634326000112/adbe-20260529.htm | E9: 2026-10-02 | F9: retrieved via WebSearch snippet; page not fetchable from this environment; restated base from Q2 FY26 10-Q
A10: ws1_price_volume | B10: Semrush revenue in Adobe Q2 FY26 | C10: ~$40M of customer-group subscription revenue (approx. 1 month) | D10: https://www.sec.gov/Archives/edgar/data/796343/000079634326000109/adbeex991q226.htm | E10: 2026-10-02 | F10: retrieved via WebSearch snippet; page not fetchable from this environment
A11: ws1_price_volume | B11: FY26 C&MP guide includes Semrush | C11: ~$280M Semrush in C&MP guide $18.21-18.27B (June 2026 raise) | D11: https://www.sec.gov/Archives/edgar/data/796343/000079634326000109/adbeex991q226.htm | E11: 2026-10-02 | F11: retrieved via WebSearch snippet; page not fetchable from this environment
A12: ws1_price_volume | B12: Adobe Q1 FY26 revenue / C&MP / BP&C | C12: $6.40B (+12% / +11% cc); C&MP $4,389M (+12% / +11% cc); BP&C $1,782M (+15-16%) | D12: https://www.sec.gov/Archives/edgar/data/796343/000079634326000048/adbeex991q126.htm | E12: 2026-10-02 | F12: retrieved via WebSearch snippet; page not fetchable from this environment; BP&C growth quoted 15% and 16% in different snippets
A13: ws1_price_volume | B13: Adobe Q1 FY26 ending ARR | C13: $26.06B, +10.9% YoY | D13: https://www.sec.gov/Archives/edgar/data/796343/000079634326000048/adbeex991q126.htm | E13: 2026-10-02 | F13: retrieved via WebSearch snippet; page not fetchable from this environment
A14: ws1_price_volume | B14: Adobe Q4 FY25 revenue; FY25 revenue | C14: $6.19B (+10%); FY25 $23.77B (+11%); Digital Media Q4 $4.62B, FY $17.65B (+11%); DM ARR $19.2B (+11.5%) | D14: https://www.sec.gov/Archives/edgar/data/796343/000079634325000135/adbeex991q425.htm | E14: 2026-10-02 | F14: retrieved via WebSearch snippet; page not fetchable from this environment
... A162: ws2_seat_compression | B162: Interpublic year-end employees 2024 | C162: 53300 | D162: https://www.sec.gov/Archives/edgar/data/51644/000005164425000024/ipg-20241231.htm | E162: 2026-10-02 | F162: retrieved via WebSearch snippet; page not fetchable from this environment. via WebSearch snippet; last standalone year
A163: ws2_seat_compression | B163: Interpublic year-end employees 2025 | D163: https://www.sec.gov/Archives/edgar/data/29989/000002998926000006/omc-20251231.htm | E163: 2026-10-02 | F163: retrieved via WebSearch snippet; page not fetchable from this environment. NOT APPLICABLE: acquired by Omnicom 26 Nov 2025; included in Omnicom 2025 figure
A164: ws2_seat_compression | B164: Indeed Hiring Lab US job postings by sector (daily index, Feb 1 2020 = 100) | C164: file | D164: https://raw.githubusercontent.com/hiring-lab/job_postings_tracker/master/US/job_postings_by_sector_US.csv | E164: 2026-10-02 | F164: downloaded 2026-10-02; last date 2026-09-25
A165: ws2_seat_compression | B165: Indeed Hiring Lab US aggregate job postings (SA/NSA) | C165: file | D165: https://raw.githubusercontent.com/hiring-lab/job_postings_tracker/master/US/aggregate_job_postings_US.csv | E165: 2026-10-02 | F165: downloaded 2026-10-02; last date 2026-09-25
A166: ws2_seat_compression | B166: Indeed creative postings Sep 2026 (Media & Comm / Marketing / Arts & Ent / Total SA) | C166: 70.7 / 76.3 / 84.2 / 103.2 | D166: https://raw.githubusercontent.com/hiring-lab/job_postings_tracker/master/US/job_postings_by_sector_US.csv | E166: 2026-10-02 | F166: monthly mean of daily index, computed in data/indeed_postings_monthly.csv
A167: ws2_seat_compression | B167: BLS OOH graphic designers 2025-35 narrative: AI/automated design tools projected to raise productivity and reduce need for workers | C167: -2% (-4,200) | D167: https://www.bls.gov/ooh/arts-and-design/graphic-designers.htm | E167: 2026-10-02 | F167: retrieved via WebSearch snippet; page not fetchable from this environment
A168: ws2_seat_compression | B168: Adobe AI research 'Economic State of Creative Professions' (Jun 2026): 5 of 9 creative occupations lost real purchasing power over the decade | C168: qualitative | D168: https://www.adobe.com/ai/research/202606/economic-state-of-creative-professions.html | E168: 2026-10-02 | F168: retrieved via WebSearch snippet; page not fetchable from this environment; adobe.com blocked
A169: ws2_seat_compression | B169: Omnicom and IPG jointly cut headcount in 2025 | C169: ~8,200 | D169: https://www.mmm-online.com/news/omnicom-and-ipg-jointly-cut-headcount-by-8200-in-2025/ | E169: 2026-10-02 | F169: retrieved via WebSearch snippet; page not fetchable from this environment
A170: ws3_task_exposure | B170: O*NET task statements for 6 occupations (102 tasks) incl. task type | C170: 19,265 task rows in file; 6 occupations n=16/16/14/23/20/13 | D170: https://raw.githubusercontent.com/openai/GPTs-are-GPTs/main/data/full_labelset.tsv | E170: 2026-10-02 | F170: downloaded; saved data/raw/gpts_full_labelset.tsv; O*NET 27.2 vintage inferred from row count
A171: ws3_task_exposure | B171: O*NET 27.2 task_statements table row count | C171: 19,265 rows | D171: https://www.onetcenter.org/dictionary/27.2/mysql/task_statements.html | E171: 2026-10-02 | F171: retrieved via WebSearch snippet; page not fetchable from this environment
A172: ws3_task_exposure | B172: Eloundou task-level exposure labels (gpt4_exposure, human_labels, alpha/beta/gamma) | C172: E0/E1/E2 per task; alpha/beta/gamma columns derive from GPT-4 label (verified) | D172: https://raw.githubusercontent.com/openai/GPTs-are-GPTs/main/data/full_labelset.tsv | E172: 2026-10-02 | F172: downloaded
A173: ws3_task_exposure | B173: Eloundou core/supplemental task weights (coreweight 2/1, equalweight) | C173: no importance weight available | D173: https://raw.githubusercontent.com/openai/GPTs-are-GPTs/main/data/full_onet_data.tsv | E173: 2026-10-02 | F173: downloaded; saved data/raw/gpts_full_onet_data.tsv
A174: ws3_task_exposure | B174: Eloundou occupation-level scores dv_rating/human_rating alpha,beta,gamma for 923 occupations | C174: e.g. Graphic Designers human gamma 0.821, human alpha 0.000 | D174: https://raw.githubusercontent.com/openai/GPTs-are-GPTs/main/data/occ_level.csv | E174: 2026-10-02 | F174: downloaded; README: dv_rating = GPT-4, human = annotators; _alpha=E1, _beta=E1+.5*E2, _gamma=E1+E2
A175: ws3_task_exposure | B175: GPTs-are-GPTs repo version | C175: last commit 2025-10-04 'Update README.md' (0471612); occ_level.csv added 2025-10-03; data files uploaded 2024-06-20 | D175: https://github.com/openai/GPTs-are-GPTs/commits/main | E175: 2026-10-02 | F175: WebFetch of commits page
... A267: ws6_channel_checks | B267: Creative Cloud Pro NA price increase June 2025 | C267: $59.99 to $69.99 per month | D267: https://helpx.adobe.com/creative-cloud/kb/creative-cloud-pro-plan-pricing-update.html | E267: 2026-10-02 | F267: URL not verified from this environment (adobe.com blocked by egress proxy); figure taken from orchestrator task context. Adobe help article on Creative Cloud Pro pricing.
